formulaic_mechanics/__init__.py
formulaic_mechanics/corpus.py
formulaic_mechanics/helpers.py
formulaic_mechanics/letters.py
formulaic_mechanics/line_sets.py
formulaic_mechanics/meter_mechanics.py
formulaic_mechanics/mutual_expectancy.py
formulaic_mechanics/n_grams.py
formulaic_mechanics/vocabulary.py
formulaic_mechanics/create_corpora/__init__.py
formulaic_mechanics/create_corpora/clean_raw_greek_files.py
formulaic_mechanics/create_corpora/hexameter.py
formulaic_mechanics/create_corpora/scan.py
formulaic_mechanics/create_corpora/scan_corpus.py
formulaic_mechanics/data/bigram_expectancies.csv
formulaic_mechanics/data/bigram_frequencies.csv
formulaic_mechanics/data/book_counts.csv
formulaic_mechanics/data/codebook.csv
formulaic_mechanics/data/compare_vocab_iliad1_odyssey1.csv
formulaic_mechanics/data/compare_vocab_iliad24_iliad1.csv
formulaic_mechanics/data/compare_vocab_iliad24_odyssey1.csv
formulaic_mechanics/data/cosine_similarities.csv
formulaic_mechanics/data/counted_words.csv
formulaic_mechanics/data/hapax_locations.csv
formulaic_mechanics/data/hemistiches.csv
formulaic_mechanics/data/iliad_lexical_diversity.csv
formulaic_mechanics/data/me_by_book_arithmetic.csv
formulaic_mechanics/data/me_by_book_geometric.csv
formulaic_mechanics/data/me_by_line.csv
formulaic_mechanics/data/me_by_line_meter_split.csv
formulaic_mechanics/data/me_by_meter.csv
formulaic_mechanics/data/metrical_pattern_counts.csv
formulaic_mechanics/data/odyssey_lexical_diversity.csv
formulaic_mechanics/data/proper_lines_by_me.csv
formulaic_mechanics/data/proper_nouns_by_me.csv
formulaic_mechanics/data/quadgram_expectancies.csv
formulaic_mechanics/data/repeated_line_sets.csv
formulaic_mechanics/data/repeated_passages.csv
formulaic_mechanics/data/repeated_passages.xlsx
formulaic_mechanics/data/trigram_expectancies.csv
formulaic_mechanics/data/unique_words_by_book.csv
formulaic_mechanics/data/vocab_overlaps.csv
formulaic_mechanics/data/word_counts.csv
formulaic_mechanics-0.0.1.dist-info/METADATA
formulaic_mechanics-0.0.1.dist-info/WHEEL
formulaic_mechanics-0.0.1.dist-info/licenses/LICENSE
formulaic_mechanics-0.0.1.dist-info/RECORD
