Metadata-Version: 2.3
Name: formulaic_mechanics
Version: 0.0.1
Summary: Computational Methods for Homeric Formulae
Project-URL: Homepage, https://github.com/AnnieKLamar/formulaic_mechanics
Project-URL: Issues, https://github.com/AnnieKLamar/formulaic_mechanics/issues
Author-email: "Annie K. Lamar" <annieklamar@gmail.com>
License-File: LICENSE
Classifier: License :: OSI Approved :: MIT License
Classifier: Operating System :: OS Independent
Classifier: Programming Language :: Python :: 3
Requires-Python: >=3.8
Requires-Dist: lexical-diversity
Requires-Dist: pandas
Requires-Dist: scipy
Requires-Dist: statsmodels
